sleepy_driver/__init__.py
sleepy_driver/cli.py
sleepy_driver/core/__init__.py
sleepy_driver/core/detector.py
sleepy_driver/core/results.py
sleepy_driver/drowsiness/__init__.py
sleepy_driver/drowsiness/analyzer.py
sleepy_driver/drowsiness/detector.py
sleepy_driver/eye/__init__.py
sleepy_driver/eye/targeting.py
sleepy_driver/models/__init__.py
sleepy_driver/models/base.py
sleepy_driver/models/eye_cnn_model.pth
sleepy_driver/models/eye_cnn_model_early_stopping.pth
sleepy_driver/models/eye_cnn_model_not_early_stopping.pth
sleepy_driver/models/ml_model.py
sleepy_driver/models/mlp_model.py
sleepy_driver/models/opencv_model.py
sleepy_driver/models/point_model.py
sleepy_driver/models/registry.py
sleepy_driver/models/rf_model.pkl
sleepy_driver-1.1.6.dist-info/licenses/LICENSE
sleepy_driver-1.1.6.dist-info/METADATA
sleepy_driver-1.1.6.dist-info/WHEEL
sleepy_driver-1.1.6.dist-info/entry_points.txt
sleepy_driver-1.1.6.dist-info/top_level.txt
sleepy_driver-1.1.6.dist-info/RECORD
