Metadata-Version: 2.4
Name: sleepy-driver
Version: 1.1.6
Summary: AI-powered drowsiness detection library for driver safety
Home-page: https://github.com/sleepy-driver/sleepy-driver
Author: SleepyDriver Team
Author-email: SleepyDriver Team <sleepy.driver@example.com>
License: MIT License
Project-URL: Homepage, https://github.com/sleepy-driver/sleepy-driver
Project-URL: Documentation, https://sleepy-driver.readthedocs.io/
Project-URL: Repository, https://github.com/sleepy-driver/sleepy-driver.git
Project-URL: Bug Tracker, https://github.com/sleepy-driver/sleepy-driver/issues
Keywords: drowsiness,detection,ai,computer-vision,safety,driver
Classifier: Development Status :: 4 - Beta
Classifier: Intended Audience :: Developers
Classifier: Topic :: Scientific/Engineering :: Artificial Intelligence
Classifier: Topic :: Software Development :: Libraries :: Python Modules
Classifier: License :: OSI Approved :: MIT License
Classifier: Programming Language :: Python :: 3
Classifier: Programming Language :: Python :: 3.8
Classifier: Programming Language :: Python :: 3.9
Classifier: Programming Language :: Python :: 3.10
Classifier: Programming Language :: Python :: 3.11
Classifier: Programming Language :: Python :: 3.12
Classifier: Operating System :: OS Independent
Requires-Python: >=3.8
License-File: LICENSE
Requires-Dist: opencv-python>=4.5.0
Requires-Dist: mediapipe>=0.10.0
Requires-Dist: numpy>=1.21.0
Provides-Extra: ml
Requires-Dist: joblib>=1.0.0; extra == "ml"
Requires-Dist: scikit-learn>=1.0.0; extra == "ml"
Provides-Extra: dl
Requires-Dist: torch>=1.9.0; extra == "dl"
Requires-Dist: torchvision>=0.10.0; extra == "dl"
Provides-Extra: all
Requires-Dist: joblib>=1.0.0; extra == "all"
Requires-Dist: scikit-learn>=1.0.0; extra == "all"
Requires-Dist: torch>=1.9.0; extra == "all"
Requires-Dist: torchvision>=0.10.0; extra == "all"
Provides-Extra: dev
Requires-Dist: pytest>=6.0; extra == "dev"
Requires-Dist: pytest-cov; extra == "dev"
Requires-Dist: black; extra == "dev"
Requires-Dist: flake8; extra == "dev"
Requires-Dist: twine; extra == "dev"
Requires-Dist: build; extra == "dev"
Requires-Dist: joblib>=1.0.0; extra == "dev"
Requires-Dist: scikit-learn>=1.0.0; extra == "dev"
Requires-Dist: torch>=1.9.0; extra == "dev"
Requires-Dist: torchvision>=0.10.0; extra == "dev"
Dynamic: author
Dynamic: home-page
Dynamic: license-file
Dynamic: requires-python
